delta_library/Call.py
delta_library/LICENSE
delta_library/Portfolio.py
delta_library/Put.py
delta_library/Stock.py
delta_library/__init__.py
delta_library/help.py
delta_library/option_pricing.py
delta_library/pyproject.toml
delta_library-0.0.2.dist-info/METADATA
delta_library-0.0.2.dist-info/WHEEL
delta_library-0.0.2.dist-info/licenses/LICENSE
delta_library-0.0.2.dist-info/RECORD
