Metadata-Version: 2.4
Name: delta_library
Version: 0.0.2
Summary: A package for modelling options and option portfolios.
Project-URL: Homepage, https://dolfbosch.nl/delta_library
Author-email: Dolf Bosch <d.c.bosch@student.rug.nl>
License-Expression: GPL-3.0-or-later
License-File: LICENSE
Classifier: Development Status :: 4 - Beta
Classifier: Intended Audience :: Financial and Insurance Industry
Classifier: License :: OSI Approved :: GNU General Public License v3 or later (GPLv3+)
Classifier: Operating System :: OS Independent
Classifier: Programming Language :: Python :: 3
Requires-Python: >=3.8
